FiinQuant/Aggregates.py
FiinQuant/Aggregates.pyi
FiinQuant/DateCorr.py
FiinQuant/DateCorr.pyi
FiinQuant/Fetch_Trading_Data.py
FiinQuant/Fetch_Trading_Data.pyi
FiinQuant/FiinIndicator.py
FiinQuant/FiinIndicator.pyi
FiinQuant/FiinQuant.py
FiinQuant/FiinQuant.pyi
FiinQuant/RealTimeData.py
FiinQuant/RealTimeData.pyi
FiinQuant/Rebalance.py
FiinQuant/Rebalance.pyi
FiinQuant/SimilarChart.py
FiinQuant/SimilarChart.pyi
FiinQuant/Trading_Data_Stream.py
FiinQuant/Trading_Data_Stream.pyi
FiinQuant/__init__.py
FiinQuant/__init__.pyi
fiinquant-0.11.22.dist-info/METADATA
fiinquant-0.11.22.dist-info/WHEEL
fiinquant-0.11.22.dist-info/top_level.txt
fiinquant-0.11.22.dist-info/RECORD
